{"stem":"1154","instances":[{"docId":"text__aratus_phaenomena","docUri":"text__aratus_phaenomena.html","score":2,"contexts":[{"form":"1154","weight":"1","pos":49,"context":"...“Things that appear”) is a didactic poem comprising <mark>1154<\/mark> hexameters composed by the poet Aratus of Soli (ca...."},{"form":"1154","weight":"1","pos":95,"context":"...advice on how to “read” them (559-<mark>1154<\/mark>). For both parts, Aratus used technical works..."}]},{"docId":"text__cicero","docUri":"text__cicero.html","score":2,"contexts":[{"form":"1154","weight":"1","pos":132,"context":"...creation of the translation. Aratus’ Phaenomena constitutes of <mark>1154<\/mark> verses divided in two main part preceded by a..."},{"form":"1154","weight":"1","pos":349,"context":"...(only 6 fragments, Aratus vv.758-<mark>1154<\/mark>)"}]},{"docId":"desc__vienna_onb_12600","docUri":"desc__vienna_onb_12600.html","score":1,"contexts":[{"form":"1154","weight":"1","pos":166,"context":"...further on the Annals for the years 1130-<mark>1154<\/mark> (6r-v changing ink and ductus). It is..."}]}]}