{"stem":"2021","instances":[{"docId":"desc__london_bl_harley_3595","docUri":"desc__london_bl_harley_3595.html","score":2,"contexts":[{"form":"2021","weight":"1","pos":1090,"context":"...catalogueShow TEI-XML     (last change: <mark>2021<\/mark>-06-14) "},{"form":"2021","weight":"1","pos":1120,"context":"..._bl_harley_3595.xml last update: <mark>2021<\/mark>-06-14)."}]},{"docId":"text__hyginus_astronomia","docUri":"text__hyginus_astronomia.html","score":2,"contexts":[{"form":"2021","weight":"1","pos":507,"context":"...(1983): 249–58.                   (draft version: <mark>2021<\/mark>-01-15)  "},{"form":"2021","weight":"1","pos":533,"context":"...hyginus_astronomia.xml - last update: <mark>2021<\/mark>-01-15)."}]},{"docId":"text__germanicus","docUri":"text__germanicus.html","score":2,"contexts":[{"form":"2021","weight":"1","pos":568,"context":"...Peter Lang, 2004.                                     (draft version: <mark>2021<\/mark>-01-15)  "},{"form":"2021","weight":"1","pos":593,"context":"...text__germanicus.xml - last update: <mark>2021<\/mark>-01-15)."}]},{"docId":"text__de_ordine_et_situ","docUri":"text__de_ordine_et_situ.html","score":2,"contexts":[{"form":"2021","weight":"1","pos":56,"context":"                (draft version: <mark>2021<\/mark>-01-15)  "},{"form":"2021","weight":"1","pos":83,"context":"...ordine_et_situ.xml - last update: <mark>2021<\/mark>-01-15)."}]},{"docId":"text__excerptum","docUri":"text__excerptum.html","score":2,"contexts":[{"form":"2021","weight":"1","pos":370,"context":".... Breslau, 1888.                                                      (draft version: <mark>2021<\/mark>-01-15)  "},{"form":"2021","weight":"1","pos":395,"context":"...text__excerptum.xml - last update: <mark>2021<\/mark>-01-15)."}]},{"docId":"desc__basle_bb_an_iv_18","docUri":"desc__basle_bb_an_iv_18.html","score":2,"contexts":[{"form":"2021","weight":"1","pos":807,"context":"...FacsimileShow TEI-XML     (last change: <mark>2021<\/mark>-01-13) "},{"form":"2021","weight":"1","pos":832,"context":"...\/desc__basle_bb_an_iv_18.xml last update: <mark>2021<\/mark>-01-13)."}]},{"docId":"text__revised_aratus_latinus","docUri":"text__revised_aratus_latinus.html","score":2,"contexts":[{"form":"2021","weight":"1","pos":194,"context":"...): 199-201.                        (draft version: <mark>2021<\/mark>-01-15)  "},{"form":"2021","weight":"1","pos":222,"context":"...aratus_latinus.xml - last update: <mark>2021<\/mark>-01-15)."}]},{"docId":"text__de_ordine","docUri":"text__de_ordine.html","score":2,"contexts":[{"form":"2021","weight":"1","pos":436,"context":"...): 293–304.                                 (draft version: <mark>2021<\/mark>-01-15)  "},{"form":"2021","weight":"1","pos":462,"context":"...text__de_ordine.xml - last update: <mark>2021<\/mark>-01-15)."}]},{"docId":"text__cicero","docUri":"text__cicero.html","score":2,"contexts":[{"form":"2021","weight":"1","pos":1021,"context":"...Aragno Editore, 2012.                      (draft version: <mark>2021<\/mark>-01-15)  "},{"form":"2021","weight":"1","pos":1046,"context":"...text__cicero.xml - last update: <mark>2021<\/mark>-01-15)."}]},{"docId":"text__avienus","docUri":"text__avienus.html","score":2,"contexts":[{"form":"2021","weight":"1","pos":436,"context":"...: VWGÖ, 1986.             (draft version: <mark>2021<\/mark>-01-15)  "},{"form":"2021","weight":"1","pos":461,"context":"...text__avienus.xml - last update: <mark>2021<\/mark>-01-15)."}]},{"docId":"text__scholia_strozziana","docUri":"text__scholia_strozziana.html","score":2,"contexts":[{"form":"2021","weight":"1","pos":192,"context":"...Dame Press, 1995.            (draft version: <mark>2021<\/mark>-01-15)  "},{"form":"2021","weight":"1","pos":218,"context":"...scholia_strozziana.xml - last update: <mark>2021<\/mark>-01-15)."}]},{"docId":"text__scholia_basileensia","docUri":"text__scholia_basileensia.html","score":2,"contexts":[{"form":"2021","weight":"1","pos":343,"context":"...Lille III, 1985.           (draft version: <mark>2021<\/mark>-01-15)  "},{"form":"2021","weight":"1","pos":369,"context":"...scholia_basileensia.xml - last update: <mark>2021<\/mark>-01-15)."}]},{"docId":"text__aratus_latinus","docUri":"text__aratus_latinus.html","score":2,"contexts":[{"form":"2021","weight":"1","pos":539,"context":"..., 506–14, 1969.         (draft version: <mark>2021<\/mark>-01-15)  "},{"form":"2021","weight":"1","pos":565,"context":"...aratus_latinus.xml - last update: <mark>2021<\/mark>-01-15)."}]}]}