{"stem":"national","instances":[{"docId":"index-mss","docUri":"index-mss.html","score":15,"contexts":[{"form":"nationale","weight":"1","pos":89,"context":"Paris, Bibliothèque <mark>nationale<\/mark> de France, MS lat. 14754"},{"form":"nationale","weight":"1","pos":159,"context":"Paris, Bibliothèque <mark>nationale<\/mark> de France, MS lat. 13955"},{"form":"nationale","weight":"1","pos":261,"context":"Paris, Bibliothèque <mark>nationale<\/mark> de France, MS lat. 7400A"},{"form":"nationale","weight":"1","pos":301,"context":"Paris Bibliothèque <mark>nationale<\/mark> de France, MS lat. 7887"},{"form":"nationale","weight":"1","pos":384,"context":"Paris, Bibliothèque <mark>nationale<\/mark> de France, MS lat. 5543"},{"form":"nationale","weight":"1","pos":417,"context":"Strasbourg, Bibliothèque <mark>nationale<\/mark> et universitaire, Ms 326"},{"form":"nationale","weight":"1","pos":429,"context":"Paris, Bibliothèque <mark>nationale<\/mark> de France, MS lat. 7886"},{"form":"nationale","weight":"1","pos":496,"context":"Paris, Bibliothèque <mark>nationale<\/mark> de France, MS lat. 12957"},{"form":"nationale","weight":"1","pos":522,"context":"Paris, Bibliothèque <mark>nationale<\/mark> de France, MS lat. 12117"},{"form":"nationale","weight":"1","pos":583,"context":"Paris, Bibliothèque <mark>nationale<\/mark> de France, MS lat. 8663"},{"form":"nationale","weight":"1","pos":608,"context":"Paris, Bibliothèque <mark>nationale<\/mark> de France, MS NAL 1614"},{"form":"nationale","weight":"1","pos":686,"context":"Paris, Bibliothèque <mark>nationale<\/mark> de France, MS lat. 5239"},{"form":"nationale","weight":"1","pos":714,"context":"Paris, Bibliothèque <mark>nationale<\/mark> de France, MS lat. 7299A"},{"form":"nationale","weight":"1","pos":795,"context":"Paris, Bibliothèque <mark>nationale<\/mark> de France, MS NAL 176"},{"form":"nationale","weight":"1","pos":939,"context":"Paris, Bibliothèque <mark>nationale<\/mark> de France, MS NAL 456"}]},{"docId":"text__excerptum","docUri":"text__excerptum.html","score":9,"contexts":[{"form":"nationale","weight":"1","pos":233,"context":"Paris, Bibliothèque <mark>nationale<\/mark> de France, MS lat. 5239"},{"form":"nationale","weight":"1","pos":239,"context":"Paris, Bibliothèque <mark>nationale<\/mark> de France, MS lat. 7299A"},{"form":"nationale","weight":"1","pos":245,"context":"Paris, Bibliothèque <mark>nationale<\/mark> de France, MS lat. 7400A"},{"form":"nationale","weight":"1","pos":251,"context":"Paris, Bibliothèque <mark>nationale<\/mark> de France, MS lat. 12117"},{"form":"nationale","weight":"1","pos":257,"context":"Paris, Bibliothèque <mark>nationale<\/mark> de France, MS lat. 13955"},{"form":"nationale","weight":"1","pos":263,"context":"Paris, Bibliothèque <mark>nationale<\/mark> de France, MS nouv. acq. lat..."},{"form":"nationale","weight":"1","pos":271,"context":"Paris, Bibliothèque <mark>nationale<\/mark> de France, MS nouv. acq. lat..."},{"form":"nationale","weight":"1","pos":279,"context":"Paris, Bibliothèque <mark>nationale<\/mark> de France, MS nouv. acq. lat..."},{"form":"nationale","weight":"1","pos":294,"context":"Strasbourg, Bibliothèque <mark>nationale<\/mark> et universitaire, Ms 326"}]},{"docId":"text__de_ordine","docUri":"text__de_ordine.html","score":6,"contexts":[{"form":"nationale","weight":"1","pos":364,"context":"Paris, Bibliothèque <mark>nationale<\/mark> de France, MS lat. 8663"},{"form":"nationale","weight":"1","pos":370,"context":"Paris, Bibliothèque <mark>nationale<\/mark> de France, MS lat. 12117"},{"form":"nationale","weight":"1","pos":376,"context":"Paris, Bibliothèque <mark>nationale<\/mark> de France, MS lat. 13955"},{"form":"nationale","weight":"1","pos":382,"context":"Paris, Bibliothèque <mark>nationale<\/mark> de France, MS NAL 1614"},{"form":"nationale","weight":"1","pos":388,"context":"Paris, Bibliothèque <mark>nationale<\/mark> de France, MS NAL 176"},{"form":"nationale","weight":"1","pos":394,"context":"Paris, Bibliothèque <mark>nationale<\/mark> de France, MS NAL 456"}]},{"docId":"text__de_signis_caeli","docUri":"text__de_signis_caeli.html","score":4,"contexts":[{"form":"nationale","weight":"1","pos":237,"context":"Paris, Bibliothèque <mark>nationale<\/mark> de France, MS lat. 5239"},{"form":"nationale","weight":"1","pos":243,"context":"Paris, Bibliothèque <mark>nationale<\/mark> de France, MS lat. 5543"},{"form":"nationale","weight":"1","pos":249,"context":"Paris, Bibliothèque <mark>nationale<\/mark> de France, MS lat. 7299A"},{"form":"nationale","weight":"1","pos":255,"context":"Paris, Bibliothèque <mark>nationale<\/mark> de France, MS lat. 14754"}]},{"docId":"desc__paris_bnf_lat_13955","docUri":"desc__paris_bnf_lat_13955.html","score":4,"contexts":[{"form":"nationale","weight":"1","pos":36,"context":"Paris, Bibliothèque <mark>nationale<\/mark> de France, MS lat. 13955 (olim..."},{"form":"nationale","weight":"1","pos":585,"context":"...on f.1r. — Acquired by the Bibliothèque <mark>nationale<\/mark> during the French revolution (see f.1r &gt;..."},{"form":"Nationale","weight":"1","pos":2300,"context":"..., \"El Herbario del manuscrito de París, Bibliothèque <mark>Nationale<\/mark>, lat. 13955, ff. 137v-146..."},{"form":"nationale","weight":"1","pos":2990,"context":"...to quote: Ivana Dobcheva, 'Paris, Bibliothèque <mark>nationale<\/mark> de France, MS lat. 13955 - Aratea..."}]},{"docId":"desc__paris_bnf_lat_7299a","docUri":"desc__paris_bnf_lat_7299a.html","score":3,"contexts":[{"form":"nationale","weight":"1","pos":36,"context":"Paris, Bibliothèque <mark>nationale<\/mark> de France, MS lat. 7299A (..."},{"form":"nationale","weight":"1","pos":304,"context":"...XIIIe s. dans les manuscrits latins de la bibliothèque <mark>nationale<\/mark> de France’. Scriptorium 52 (1998): 102..."},{"form":"nationale","weight":"1","pos":945,"context":"...to quote: Ivana Dobcheva, 'Paris, Bibliothèque <mark>nationale<\/mark> de France, MS lat. 7299A -..."}]},{"docId":"desc__paris_bnf_lat_12117","docUri":"desc__paris_bnf_lat_12117.html","score":3,"contexts":[{"form":"nationale","weight":"1","pos":36,"context":"Paris, Bibliothèque <mark>nationale<\/mark> de France, MS lat. 12117FacsimileShow..."},{"form":"Nationale","weight":"1","pos":448,"context":"...lieu ou de copiste. Vol. 3: Bibliothèque <mark>Nationale<\/mark>, fonds latin Nos. 8001 à 18613...."},{"form":"nationale","weight":"1","pos":2035,"context":"...to quote: Ivana Dobcheva, 'Paris, Bibliothèque <mark>nationale<\/mark> de France, MS lat. 12117 - Aratea..."}]},{"docId":"text__revised_aratus_latinus","docUri":"text__revised_aratus_latinus.html","score":3,"contexts":[{"form":"nationale","weight":"1","pos":137,"context":"Paris, Bibliothèque <mark>nationale<\/mark> de France, MS lat. 12957"},{"form":"nationale","weight":"1","pos":143,"context":"Paris, Bibliothèque <mark>nationale<\/mark> de France, MS NAL 176"},{"form":"nationale","weight":"1","pos":149,"context":"Paris, Bibliothèque <mark>nationale<\/mark> de France, MS NAL 1614"}]},{"docId":"desc__paris_bnf_lat_14754","docUri":"desc__paris_bnf_lat_14754.html","score":3,"contexts":[{"form":"nationale","weight":"1","pos":36,"context":"Paris, Bibliothèque <mark>nationale<\/mark> de France, MS lat. 14754FacsimileShow..."},{"form":"nationale","weight":"1","pos":182,"context":"...bibliography:David Juste, ‘MS Paris, Bibliothèque <mark>nationale<\/mark> de France, lat. 14754’ (update..."},{"form":"nationale","weight":"1","pos":511,"context":"...to quote: Ivana Dobcheva, 'Paris, Bibliothèque <mark>nationale<\/mark> de France, MS lat. 14754 - Aratea..."}]},{"docId":"desc__paris_bnf_lat_8663","docUri":"desc__paris_bnf_lat_8663.html","score":3,"contexts":[{"form":"nationale","weight":"1","pos":36,"context":"Paris, Bibliothèque <mark>nationale<\/mark> de France, MS lat. 8663 (olim..."},{"form":"nationale","weight":"1","pos":209,"context":"...† sur quelques manuscrits latins anciens de la Bibliothèque <mark>nationale<\/mark> de Paris.”Bulletin d’information de l’Institut de Recherche..."},{"form":"nationale","weight":"1","pos":1103,"context":"...to quote: Ivana Dobcheva, 'Paris, Bibliothèque <mark>nationale<\/mark> de France, MS lat. 8663 - Aratea..."}]},{"docId":"text__germanicus","docUri":"text__germanicus.html","score":3,"contexts":[{"form":"nationale","weight":"1","pos":492,"context":"Paris, Bibliothèque <mark>nationale<\/mark> de France, MS lat. 7886"},{"form":"nationale","weight":"1","pos":498,"context":"Paris, Bibliothèque <mark>nationale<\/mark> de France, MS lat. 5239"},{"form":"nationale","weight":"1","pos":504,"context":"Strasbourg, Bibliothèque <mark>nationale<\/mark> et universitaire, Ms 326"}]},{"docId":"text__scholia_basileensia","docUri":"text__scholia_basileensia.html","score":3,"contexts":[{"form":"nationale","weight":"1","pos":326,"context":"Paris, Bibliothèque <mark>nationale<\/mark> de France, MS lat. 5239"},{"form":"nationale","weight":"1","pos":332,"context":"Paris, Bibliothèque <mark>nationale<\/mark> de France, MS lat. 7886"},{"form":"nationale","weight":"1","pos":338,"context":"Strasbourg, Bibliothèque <mark>nationale<\/mark> et universitaire, Ms 326"}]},{"docId":"text__abbo_hyginus","docUri":"text__abbo_hyginus.html","score":3,"contexts":[{"form":"nationale","weight":"1","pos":56,"context":"Paris, Bibliothèque <mark>nationale<\/mark> de France, MS lat. 7400A"},{"form":"nationale","weight":"1","pos":82,"context":"Paris, Bibliothèque <mark>nationale<\/mark> de France, MS lat. 7518 (?)"},{"form":"nationale","weight":"1","pos":88,"context":"Paris, Bibliothèque <mark>nationale<\/mark> de France, MS lat. 17868 (?)"}]},{"docId":"desc__strasbourg_bnu_326","docUri":"desc__strasbourg_bnu_326.html","score":2,"contexts":[{"form":"nationale","weight":"1","pos":36,"context":"Strasbourg, Bibliothèque <mark>nationale<\/mark> et universitaire, Ms 326 (olim: Latin..."},{"form":"nationale","weight":"1","pos":2712,"context":"...to quote: Ivana Dobcheva, 'Strasbourg, Bibliothèque <mark>nationale<\/mark> et universitaire, Ms 326 - Aratea Digital' (..."}]},{"docId":"text__hyginus_astronomia","docUri":"text__hyginus_astronomia.html","score":2,"contexts":[{"form":"nationale","weight":"1","pos":455,"context":"Paris, Bibliothèque <mark>nationale<\/mark> de France, MS lat. 7299A"},{"form":"nationale","weight":"1","pos":466,"context":"Paris, Bibliothèque <mark>nationale<\/mark> de France, MS lat. 8728 (digitised..."}]},{"docId":"desc__paris_bnf_lat_5239","docUri":"desc__paris_bnf_lat_5239.html","score":2,"contexts":[{"form":"nationale","weight":"1","pos":36,"context":"Paris, Bibliothèque <mark>nationale<\/mark> de France, MS lat. 5239FacsimileShow..."},{"form":"nationale","weight":"1","pos":908,"context":"...to quote: Ivana Dobcheva, 'Paris, Bibliothèque <mark>nationale<\/mark> de France, MS lat. 5239 - Aratea..."}]},{"docId":"desc__paris_bnf_nal_1614","docUri":"desc__paris_bnf_nal_1614.html","score":2,"contexts":[{"form":"nationale","weight":"1","pos":36,"context":"Paris, Bibliothèque <mark>nationale<\/mark> de France, MS NAL 1614FacsimileShow TEI..."},{"form":"nationale","weight":"1","pos":859,"context":"...to quote: Ivana Dobcheva, 'Paris, Bibliothèque <mark>nationale<\/mark> de France, MS NAL 1614 - Aratea Digital'..."}]},{"docId":"desc__paris_bnf_lat_7886","docUri":"desc__paris_bnf_lat_7886.html","score":2,"contexts":[{"form":"nationale","weight":"1","pos":36,"context":"Paris, Bibliothèque <mark>nationale<\/mark> de France, MS lat. 7886 (olim..."},{"form":"nationale","weight":"1","pos":856,"context":"...to quote: Ivana Dobcheva, 'Paris, Bibliothèque <mark>nationale<\/mark> de France, MS lat. 7886 - Aratea..."}]},{"docId":"desc__paris_bnf_lat_12957","docUri":"desc__paris_bnf_lat_12957.html","score":2,"contexts":[{"form":"nationale","weight":"1","pos":36,"context":"Paris, Bibliothèque <mark>nationale<\/mark> de France, MS lat. 12957FacsimileShow..."},{"form":"nationale","weight":"1","pos":1582,"context":"...to quote: Ivana Dobcheva, 'Paris, Bibliothèque <mark>nationale<\/mark> de France, MS lat. 12957 - Aratea..."}]},{"docId":"desc__paris_bnf_lat_5543","docUri":"desc__paris_bnf_lat_5543.html","score":2,"contexts":[{"form":"nationale","weight":"1","pos":36,"context":"Paris, Bibliothèque <mark>nationale<\/mark> de France, MS lat. 5543FacsimileShow..."},{"form":"nationale","weight":"1","pos":2377,"context":"...to quote: Ivana Dobcheva, 'Paris, Bibliothèque <mark>nationale<\/mark> de France, MS lat. 5543 - Aratea..."}]},{"docId":"desc__paris_bnf_lat_7400A","docUri":"desc__paris_bnf_lat_7400A.html","score":2,"contexts":[{"form":"nationale","weight":"1","pos":36,"context":"Paris, Bibliothèque <mark>nationale<\/mark> de France, MS lat. 7400AFacsimile..."},{"form":"nationale","weight":"1","pos":248,"context":"...to quote: Ivana Dobcheva, 'Paris, Bibliothèque <mark>nationale<\/mark> de France, MS lat. 7400A -..."}]},{"docId":"desc__paris_bnf_nal_456","docUri":"desc__paris_bnf_nal_456.html","score":2,"contexts":[{"form":"nationale","weight":"1","pos":36,"context":"Paris, Bibliothèque <mark>nationale<\/mark> de France, MS NAL 456FacsimileShow TEI..."},{"form":"nationale","weight":"1","pos":923,"context":"...to quote: Ivana Dobcheva, 'Paris, Bibliothèque <mark>nationale<\/mark> de France, MS NAL 456 - Aratea Digital'..."}]},{"docId":"desc__paris_bnf_lat_7887","docUri":"desc__paris_bnf_lat_7887.html","score":2,"contexts":[{"form":"nationale","weight":"1","pos":36,"context":"Paris Bibliothèque <mark>nationale<\/mark> de France, MS lat. 7887 (olim..."},{"form":"nationale","weight":"1","pos":539,"context":"...How to quote: Ivana Dobcheva, 'Paris Bibliothèque <mark>nationale<\/mark> de France, MS lat. 7887 - Aratea..."}]},{"docId":"desc__paris_bnf_nal_176","docUri":"desc__paris_bnf_nal_176.html","score":2,"contexts":[{"form":"nationale","weight":"1","pos":36,"context":"Paris, Bibliothèque <mark>nationale<\/mark> de France, MS NAL 176FacsimileShow TEI..."},{"form":"nationale","weight":"1","pos":587,"context":"...to quote: Ivana Dobcheva, 'Paris, Bibliothèque <mark>nationale<\/mark> de France, MS NAL 176 - Aratea Digital..."}]},{"docId":"text__aratus_latinus","docUri":"text__aratus_latinus.html","score":2,"contexts":[{"form":"nationale","weight":"1","pos":527,"context":" Paris, Bibliothèque <mark>nationale<\/mark> de France, MS lat. 7886"},{"form":"nationale","weight":"1","pos":533,"context":" Paris, Bibliothèque <mark>nationale<\/mark> de France, MS lat. 7887"}]},{"docId":"text__de_ordine_et_situ","docUri":"text__de_ordine_et_situ.html","score":1,"contexts":[{"form":"nationale","weight":"1","pos":50,"context":"Paris, Bibliothèque <mark>nationale<\/mark> de France, MS NAL 456"}]},{"docId":"desc__madrid_bn_19","docUri":"desc__madrid_bn_19.html","score":1,"contexts":[{"form":"nationale","weight":"1","pos":103,"context":"...\"Un manuscrit de comput mal connu de la Bibliotheque <mark>nationale<\/mark> de Madrid,\" in Revista de Archivos, Bibliotecas..."}]},{"docId":"desc__bav_vat_lat_1783","docUri":"desc__bav_vat_lat_1783.html","score":1,"contexts":[{"form":"nationale","weight":"1","pos":220,"context":"...Wilmart sur quelques manuscrits latins anciens de la Bibliothek <mark>nationale<\/mark> de Paris\" in Bulletin d'information de l'Institut de recherche..."}]},{"docId":"desc__bav_reg_lat_309","docUri":"desc__bav_reg_lat_309.html","score":1,"contexts":[{"form":"nationale","weight":"1","pos":123,"context":"...The same text present also in Paris, Bibliothèque <mark>nationale<\/mark> de France, MS lat. 12117 and Strasbourg..."}]},{"docId":"desc__valenciennes_bm_343","docUri":"desc__valenciennes_bm_343.html","score":1,"contexts":[{"form":"nationale","weight":"1","pos":434,"context":"...Delisle,Le cabinet des manuscrits de la Bibliothèque impériale <mark>nationale<\/mark>, 3 vols. (Paris, 1868-81),..."}]}]}