{"stem":"scripuli","instances":[{"docId":"desc__paris_bnf_lat_12117","docUri":"desc__paris_bnf_lat_12117.html","score":2,"contexts":[{"form":"scripulis","weight":"1","pos":652,"context":"...Uncia uiginti scripulos et quattuor ambit … — … <mark>scripulis<\/mark> seu gramma retentant. 2v Fulbert of Chartres:..."},{"form":"scripuli","weight":"1","pos":666,"context":"...›De scripulo et partibus eius‹ Unus item <mark>scripuli<\/mark> calcis componitur octo … — … calcus ciceris duo..."}]},{"docId":"desc__strasbourg_bnu_326","docUri":"desc__strasbourg_bnu_326.html","score":1,"contexts":[{"form":"scripuli","weight":"1","pos":1533,"context":"...Scripulus - sex siliquae | Dimidia sextula - duo <mark>scripuli<\/mark> et siliquae xii … — … Assis siue as..."}]},{"docId":"desc__london_bl_harley_3595","docUri":"desc__london_bl_harley_3595.html","score":1,"contexts":[{"form":"scripuli","weight":"1","pos":817,"context":"...-73r) Uncia multiplicata per CCLXXXVIII quia tot <mark>scripuli<\/mark> sunt … — … Hos cum XII augeas quomodo..."}]},{"docId":"desc__bamberg_sb_class_55","docUri":"desc__bamberg_sb_class_55.html","score":1,"contexts":[{"form":"scripuli","weight":"1","pos":800,"context":"...Scripulus - sex siliquae | Dimidia sextula - duo <mark>scripuli<\/mark> et siliquae xii … — … Assis siue as..."}]}]}